bpnext/_version.py
bpnext/io/base.py
bpnext/io/dbsf.py
bpnext/io/hdf5.py
bpnext/models/__init__.py
bpnext/models/_mixins.py
bpnext/models/bpnet.py
bpnext/models/chrombpnet.py
bpnext/models/dragonnfruit.py
bpnext/utils/losses.py
bpnext-0.0.1.dist-info/METADATA
bpnext-0.0.1.dist-info/WHEEL
bpnext-0.0.1.dist-info/licenses/LICENSE
bpnext-0.0.1.dist-info/RECORD
