Metadata-Version: 2.4
Name: bpnext
Version: 0.0.1
Summary: yet another BPNet implementation in PyTorch
Project-URL: Repository, https://github.com/gtca/bpnext.git
Project-URL: Bug Tracker, https://github.com/gtca/bpnext/issues
Author-email: Danila Bredikhin <danila@stanford.edu>
License: MIT
License-File: LICENSE
Keywords: ATAC,BPNet,CNN,DNA,chromatin,deep learning
Classifier: Development Status :: 3 - Alpha
Classifier: Intended Audience :: Science/Research
Classifier: License :: OSI Approved :: MIT License
Classifier: Operating System :: OS Independent
Classifier: Programming Language :: Python :: 3
Classifier: Programming Language :: Python :: 3.9
Classifier: Programming Language :: Python :: 3.10
Classifier: Programming Language :: Python :: 3.11
Classifier: Topic :: Scientific/Engineering :: Bio-Informatics
Requires-Python: >=3.11
Requires-Dist: numpy>=1.25.0
Requires-Dist: torch>=2.0.0
Provides-Extra: docs
Requires-Dist: furo; extra == 'docs'
Requires-Dist: myst-parser; extra == 'docs'
Requires-Dist: sphinx; extra == 'docs'
Requires-Dist: sphinx-autodoc-typehints; extra == 'docs'
Requires-Dist: sphinx-autosummary-accessors; extra == 'docs'
Requires-Dist: sphinx-rtd-theme; extra == 'docs'
Provides-Extra: io
Requires-Dist: h5py; extra == 'io'
Provides-Extra: test
Requires-Dist: bpnet-lite; extra == 'test'
Requires-Dist: h5py; extra == 'test'
Requires-Dist: pytest; extra == 'test'
